packaging_utils/__init__.py
packaging_utils/anitya/__init__.py
packaging_utils/anitya/check_anitya.py
packaging_utils/changelog_extractor/__init__.py
packaging_utils/changelog_extractor/changelog_extractor.py
packaging_utils/changelog_extractor/helpers.py
packaging_utils/common/__init__.py
packaging_utils/common/config.py
packaging_utils/common/conversion.py
packaging_utils/common/helpers.py
packaging_utils/common/zypper.py
packaging_utils/librariesio/__init__.py
packaging_utils/librariesio/get_latest_version.py
packaging_utils/specfile/__init__.py
packaging_utils/specfile/helpers.py
packaging_utils/specfile/license_rewriter.py
packaging_utils/specfile/version_updater.py
packaging_utils-0.2.5.data/scripts/branch-and-fix-license.sh
packaging_utils-0.2.5.data/scripts/update-packages.sh
tests/__init__.py
tests/changelog_extractor/__init__.py
tests/changelog_extractor/test_base.py
tests/changelog_extractor/test_confluence.py
tests/changelog_extractor/test_debian.py
tests/changelog_extractor/test_git.py
tests/changelog_extractor/test_github.py
tests/changelog_extractor/test_helpers.py
tests/changelog_extractor/test_md.py
tests/changelog_extractor/test_misp.py
tests/changelog_extractor/test_rst.py
tests/common/__init__.py
tests/common/test_conversion.py
tests/specfile/__init__.py
tests/specfile/test_helpers.py
packaging_utils-0.2.5.dist-info/COPYING
packaging_utils-0.2.5.dist-info/METADATA
packaging_utils-0.2.5.dist-info/WHEEL
packaging_utils-0.2.5.dist-info/entry_points.txt
packaging_utils-0.2.5.dist-info/top_level.txt
packaging_utils-0.2.5.dist-info/RECORD
