Metadata-Version: 2.1
Name: packaging-utils
Version: 0.2.5
Summary: My packaging utilites.
Home-page: UNKNOWN
Maintainer: Sebastian Wagner
Maintainer-email: sebix@sebix.at
License: ISC
Keywords: packaging update check anitya release-monitoring opensuse
Platform: UNKNOWN
Classifier: Development Status :: 4 - Beta
Classifier: Environment :: Console
Classifier: Intended Audience :: Developers
Classifier: Intended Audience :: Information Technology
Classifier: License :: OSI Approved :: ISC License (ISCL)
Classifier: Operating System :: POSIX :: Linux
Classifier: Programming Language :: Python
Classifier: Programming Language :: Python :: 3
Classifier: Programming Language :: Python :: 3.6
Classifier: Programming Language :: Python :: 3.7
Classifier: Programming Language :: Python :: 3.8
Classifier: Programming Language :: Python :: 3.9
Classifier: Programming Language :: Python :: 3 :: Only
Classifier: Programming Language :: Python :: Implementation :: CPython
Classifier: Topic :: System :: Archiving :: Packaging
Requires-Python: >=3.6
License-File: COPYING
Requires-Dist: requests
